core/__init__.py
core/cache/__init__.py
core/cache/akshare_adapter.py
core/database/__init__.py
core/database/connection.py
core/models/__init__.py
core/models/asset.py
core/models/financial_data.py
core/models/index_data.py
core/models/realtime_data.py
core/models/stock_data.py
core/models/stock_list.py
core/models/system_metrics.py
core/services/__init__.py
core/services/asset_info_service.py
core/services/database_cache.py
core/services/financial_data_service.py
core/services/index_data_service.py
core/services/monitoring_middleware.py
core/services/monitoring_service.py
core/services/query_service.py
core/services/realtime_data_service.py
core/services/service_manager.py
core/services/stock_data_service.py
core/services/stock_list_service.py
core/services/trading_calendar.py
core/utils/__init__.py
core/utils/config.py
core/utils/helpers.py
core/utils/logger.py
core/utils/validators.py
qdb/README.md
qdb/__init__.py
qdb/client.py
qdb/exceptions.py
quantdb-2.2.12.dist-info/LICENSE
quantdb-2.2.12.dist-info/METADATA
quantdb-2.2.12.dist-info/WHEEL
quantdb-2.2.12.dist-info/top_level.txt
quantdb-2.2.12.dist-info/RECORD
