Metadata-Version: 2.1
Name: quantdb
Version: 2.2.12
Summary: Intelligent caching wrapper for AKShare with 90%+ performance boost - 100% English codebase (import as 'qdb')
Home-page: https://github.com/franksunye/quantdb
Author: Ye Sun
Author-email: franksunye@hotmail.com
License: MIT
Project-URL: Bug Reports, https://github.com/franksunye/quantdb/issues
Project-URL: Source, https://github.com/franksunye/quantdb
Project-URL: Documentation, https://franksunye.github.io/quantdb/
Keywords: stock,finance,akshare,cache,quantitative,trading,investment,qdb,quantdb
Platform: any
Classifier: Development Status :: 4 - Beta
Classifier: Intended Audience :: Developers
Classifier: Intended Audience :: Financial and Insurance Industry
Classifier: Topic :: Office/Business :: Financial :: Investment
Classifier: Topic :: Software Development :: Libraries :: Python Modules
Classifier: License :: OSI Approved :: MIT License
Classifier: Programming Language :: Python :: 3
Classifier: Programming Language :: Python :: 3.8
Classifier: Programming Language :: Python :: 3.9
Classifier: Programming Language :: Python :: 3.10
Classifier: Programming Language :: Python :: 3.11
Classifier: Operating System :: OS Independent
Requires-Python: >=3.8
License-File: LICENSE
Requires-Dist: akshare (>=1.0.0)
Requires-Dist: beautifulsoup4 (>=4.12.3)
Requires-Dist: numpy (>=1.20.0)
Requires-Dist: pandas-market-calendars (>=4.0.0)
Requires-Dist: pandas (>=1.3.0)
Requires-Dist: python-dateutil (>=2.8.0)
Requires-Dist: sqlalchemy (>=1.4.0)
Requires-Dist: tenacity (!=8.4.0,>=8.2.3)
Provides-Extra: dev
Requires-Dist: black (>=21.0.0) ; extra == 'dev'
Requires-Dist: flake8 (>=3.9.0) ; extra == 'dev'
Requires-Dist: mypy (>=0.910) ; extra == 'dev'
Requires-Dist: pytest-cov (>=2.12.0) ; extra == 'dev'
Requires-Dist: pytest (>=6.2.0) ; extra == 'dev'
Provides-Extra: docs
Requires-Dist: sphinx-rtd-theme (>=0.5.0) ; extra == 'docs'
Requires-Dist: sphinx (>=4.0.0) ; extra == 'docs'
Provides-Extra: full
Requires-Dist: fastapi (>=0.68.0) ; extra == 'full'
Requires-Dist: httpx (>=0.18.0) ; extra == 'full'
Requires-Dist: pydantic (>=1.8.0) ; extra == 'full'
Requires-Dist: python-dotenv (>=0.19.0) ; extra == 'full'
Requires-Dist: uvicorn (>=0.15.0) ; extra == 'full'
